kmcos/__init__.py
kmcos/cli.py
kmcos/config.py
kmcos/io.py
kmcos/kmc_editor.glade
kmcos/kmc_project_v0.1.dtd
kmcos/kmc_project_v0.2.dtd
kmcos/kmc_project_v0.3.dtd
kmcos/kmc_project_v0.4.dtd
kmcos/runfile_init.py
kmcos/snapshots.py
kmcos/snapshots_globals.py
kmcos/species.py
kmcos/throttling.py
kmcos/throttling_globals.py
kmcos/types.py
kmcos/units.py
kmcos/view.py
kmcos/fortran_src/assert.ppc
kmcos/fortran_src/base.mpy
kmcos/fortran_src/base_acc.f90
kmcos/fortran_src/base_acf.mpy
kmcos/fortran_src/base_lat_int.mpy
kmcos/fortran_src/base_lat_int_acc.f90
kmcos/fortran_src/base_otf.f90
kmcos/fortran_src/kind_values.f90
kmcos/fortran_src/lattice.mpy
kmcos/fortran_src/lattice_acc.mpy
kmcos/fortran_src/main.f90
kmcos/fortran_src/proclist_constants.mpy
kmcos/fortran_src/proclist_constants_acc.mpy
kmcos/fortran_src/proclist_constants_otf.mpy
kmcos/fortran_src/proclist_generic_subroutines.mpy
kmcos/fortran_src/proclist_generic_subroutines_acc.mpy
kmcos/fortran_src/proclist_generic_subroutines_acf.mpy
kmcos/fortran_src/proclist_pars_otf.mpy
kmcos/gui/__init__.py
kmcos/gui/forms.py
kmcos/interactions/BEPmodule.py
kmcos/interactions/__init__.py
kmcos/interactions/cleanCoordinates.py
kmcos/interactions/cleanSites.py
kmcos/interactions/configurationsAndInteractions.py
kmcos/run/__init__.py
kmcos/run/acf.py
kmcos/run/png.py
kmcos/run/steady_state.py
kmcos/utils/__init__.py
kmcos/utils/ordered_dict.py
kmcos/utils/progressbar.py
kmcos/utils/terminal.py
kmcos-1.1.0.data/scripts/kmcos.bat
kmcos-1.1.0.data/scripts/kmos.bat
kmcos-1.1.0.dist-info/COPYING
kmcos-1.1.0.dist-info/METADATA
kmcos-1.1.0.dist-info/WHEEL
kmcos-1.1.0.dist-info/top_level.txt
kmcos-1.1.0.dist-info/RECORD
