Metadata-Version: 2.1
Name: kmcos
Version: 1.1.0
Summary: kMC modeling on steroids
Home-page: https://github.com/kmcos/kmcos
Author: Max J. Hoffmann
Author-email: mjhoffmann@gmail.com
Maintainer: Aditya Savara
Maintainer-email: AdityaSavara2008@u.northwestern.edu
License: COPYING
Platform: linux
Platform: windows
Provides-Extra: complete
Requires-Dist: ipython ; extra == 'complete'
Requires-Dist: numpy ; extra == 'complete'
Requires-Dist: lxml ; extra == 'complete'
Requires-Dist: ase ; extra == 'complete'
Requires-Dist: kiwi-gtk ; extra == 'complete'
Requires-Dist: dill ; extra == 'complete'
Requires-Dist: pycairo (==1.11.1) ; extra == 'complete'
Requires-Dist: pygobject (==3.30) ; extra == 'complete'
Requires-Dist: UnitTesterSG ; extra == 'complete'
Requires-Dist: CiteSoft ; extra == 'complete'
Requires-Dist: pytest ; extra == 'complete'
Requires-Dist: moviepy ; extra == 'complete'
Provides-Extra: minimal
Requires-Dist: ipython ; extra == 'minimal'
Requires-Dist: numpy ; extra == 'minimal'
Requires-Dist: lxml ; extra == 'minimal'
Requires-Dist: ase ; extra == 'minimal'
Requires-Dist: UnitTesterSG ; extra == 'minimal'
Requires-Dist: CiteSoft ; extra == 'minimal'
Provides-Extra: windows
Requires-Dist: ipython ; extra == 'windows'
Requires-Dist: numpy ; extra == 'windows'
Requires-Dist: lxml ; extra == 'windows'
Requires-Dist: ase ; extra == 'windows'
Requires-Dist: UnitTesterSG ; extra == 'windows'
Requires-Dist: CiteSoft ; extra == 'windows'
Requires-Dist: windows-curses ; extra == 'windows'
